odoo9_addon_document_page_work_instruction-9.0.1.0.0.99.dev10-py2.7-nspkg.pth
odoo9_addon_document_page_work_instruction-9.0.1.0.0.99.dev10.dist-info/DESCRIPTION.rst
odoo9_addon_document_page_work_instruction-9.0.1.0.0.99.dev10.dist-info/METADATA
odoo9_addon_document_page_work_instruction-9.0.1.0.0.99.dev10.dist-info/RECORD
odoo9_addon_document_page_work_instruction-9.0.1.0.0.99.dev10.dist-info/WHEEL
odoo9_addon_document_page_work_instruction-9.0.1.0.0.99.dev10.dist-info/metadata.json
odoo9_addon_document_page_work_instruction-9.0.1.0.0.99.dev10.dist-info/namespace_packages.txt
odoo9_addon_document_page_work_instruction-9.0.1.0.0.99.dev10.dist-info/top_level.txt
odoo_addons/document_page_work_instruction/README.rst
odoo_addons/document_page_work_instruction/__init__.py
odoo_addons/document_page_work_instruction/__openerp__.py
odoo_addons/document_page_work_instruction/data/document_page.xml
odoo_addons/document_page_work_instruction/i18n/de.po
odoo_addons/document_page_work_instruction/i18n/es.po
odoo_addons/document_page_work_instruction/i18n/fr.po
odoo_addons/document_page_work_instruction/i18n/nb.po
odoo_addons/document_page_work_instruction/i18n/nn.po
odoo_addons/document_page_work_instruction/i18n/no.po
odoo_addons/document_page_work_instruction/i18n/pt_BR.po
odoo_addons/document_page_work_instruction/i18n/sl.po
odoo_addons/document_page_work_instruction/i18n/vi.po
odoo_addons/document_page_work_instruction/migrations/7.0.1.0/pre-migration.py
odoo_addons/document_page_work_instruction/static/description/icon.png
odoo_addons/document_page_work_instruction/views/document_page_work_instructions.xml
